<annotation>
	<folder>line_brown</folder>
	<filename>line_brown56.jpg</filename>
	<path>/Users/lanbig/Desktop/line_brown/line_brown56.jpg</path>
	<source>
		<database>Unknown</database>
	</source>
	<size>
		<width>185</width>
		<height>158</height>
		<depth>3</depth>
	</size>
	<segmented>0</segmented>
	<object>
		<name>line_brown</name>
		<pose>Unspecified</pose>
		<truncated>0</truncated>
		<difficult>0</difficult>
		<bndbox>
			<xmin>103</xmin>
			<ymin>62</ymin>
			<xmax>142</xmax>
			<ymax>103</ymax>
		</bndbox>
	</object>
</annotation>
